MANIFEST.in
account_tax.xml
account_tax_code.xml
l10n_cl_chart.xml
l10n_cl_wizard.xml
setup.py
./__init__.py
./__openerp__.py
i18n/es.po
i18n/es_CL.po
i18n/l10n_cl.pot
i18n/nl.po
i18n/pt_BR.po
i18n/sl.po
i18n/tr.po
i18n/zh_CN.po
images/config_chart_l10n_cl.jpeg
images/l10n_cl_chart.jpeg
openerp_l10n_cl.egg-info/PKG-INFO
openerp_l10n_cl.egg-info/SOURCES.txt
openerp_l10n_cl.egg-info/dependency_links.txt
openerp_l10n_cl.egg-info/requires.txt
openerp_l10n_cl.egg-info/top_level.txt
static/src/img/icon.png